{
    "name": "product_category",
    "relation": [
        {
            "model": "shop",
            "type": "one-to-one"
        },
        {
            "model": "product",
            "type": "one-to-one"
        }
    ],
    "description": "table : product_to_category",
    "data": [
        {
            "name": "product_id",
            "description": "",
            "type": "integer",
            "required": false
        },
        {
            "name": "shop_id",
            "description": "",
            "type": "integer",
            "required": false
        }
    ]
}