[
	{
		"path": "GET /manage/manager",
		"description": "return list of manager",
		"parameters" : {
			"required" : [],
			"optional" : []
		},
		"response" : {
			"product" : {
				"description" : [],
				"type" : []
				}
		}
	},

	{
		"path": "POST /manage/manager",
		"description": "add new manager",
		"parameters" : {
			"required" : [],
			"optional" : []
		},
		"response" : {
			"manager" : {
				"description" : ["name"],
				"type" :[]
				}
		}
	},

	{
		"path": "DELETE /manage/managerId",
		"description": "delete manger",
		"parameters" : {
			"required" : [],
			"optional" : []
		},
		"response" : {
			"manager" : {
				"description" : [],
				"type" :[]
				}
		}
	}
]

